LICENSE
MANIFEST.in
README.md
extra_requirements.json
vectorhub/__init__.py
vectorhub/_version.py
vectorhub/auto_encoder.py
vectorhub/base.py
vectorhub/doc_utils.py
vectorhub/errors.py
vectorhub/import_utils.py
vectorhub/indexer.py
vectorhub/models_dict.py
vectorhub/options.py
vectorhub/utils.py
vectorhub/bi_encoders/__init__.py
vectorhub/bi_encoders/qa/__init__.py
vectorhub/bi_encoders/qa/base.py
vectorhub/bi_encoders/qa/sentence_transformers/__init__.py
vectorhub/bi_encoders/qa/sentence_transformers/distilroberta_qa.md
vectorhub/bi_encoders/qa/sentence_transformers/distilroberta_qa.py
vectorhub/bi_encoders/qa/tfhub/__init__.py
vectorhub/bi_encoders/qa/tfhub/lareqa_qa.md
vectorhub/bi_encoders/qa/tfhub/lareqa_qa.py
vectorhub/bi_encoders/qa/tfhub/use_multi_qa.md
vectorhub/bi_encoders/qa/tfhub/use_multi_qa.py
vectorhub/bi_encoders/qa/tfhub/use_qa.md
vectorhub/bi_encoders/qa/tfhub/use_qa.py
vectorhub/bi_encoders/qa/torch_transformers/__init__.py
vectorhub/bi_encoders/qa/torch_transformers/dpr.md
vectorhub/bi_encoders/qa/torch_transformers/dpr.py
vectorhub/bi_encoders/text_image/__init__.py
vectorhub/bi_encoders/text_image/torch/__init__.py
vectorhub/bi_encoders/text_image/torch/clip.md
vectorhub/bi_encoders/text_image/torch/clip.py
vectorhub/encoders/__init__.py
vectorhub/encoders/audio/__init__.py
vectorhub/encoders/audio/base.py
vectorhub/encoders/audio/pytorch/__init__.py
vectorhub/encoders/audio/pytorch/wav2vec.md
vectorhub/encoders/audio/pytorch/wav2vec.py
vectorhub/encoders/audio/tfhub/__init__.py
vectorhub/encoders/audio/tfhub/speech_embedding.md
vectorhub/encoders/audio/tfhub/speech_embedding.py
vectorhub/encoders/audio/tfhub/trill.md
vectorhub/encoders/audio/tfhub/trill.py
vectorhub/encoders/audio/tfhub/trill_distilled.md
vectorhub/encoders/audio/tfhub/trill_distilled.py
vectorhub/encoders/audio/tfhub/vggish.md
vectorhub/encoders/audio/tfhub/vggish.py
vectorhub/encoders/audio/tfhub/yamnet.md
vectorhub/encoders/audio/tfhub/yamnet.py
vectorhub.egg-info/PKG-INFO
vectorhub.egg-info/SOURCES.txt
vectorhub.egg-info/dependency_links.txt
vectorhub.egg-info/requires.txt
vectorhub.egg-info/top_level.txt
vectorhub-1.8.3.dist-info/LICENSE
vectorhub-1.8.3.dist-info/METADATA
vectorhub-1.8.3.dist-info/WHEEL
vectorhub-1.8.3.dist-info/top_level.txt
vectorhub-1.8.3.dist-info/RECORD
