Metadata-Version: 2.1
Name: vectorhub
Version: 1.8.3
Summary: One liner to encode data into vectors with state-of-the-art models using tensorflow, pytorch and other open source libraries. Word2Vec, Image2Vec, BERT, etc
Home-page: https://github.com/vector-ai/vectorhub
Author: OnSearch Pty Ltd
Author-email: dev@vctr.ai
License: Apache
Keywords: vector,embeddings,machinelearning,ai,artificialintelligence,nlp,tensorflow,pytorch,nearestneighbors,search,analytics,clustering,dimensionalityreduction
Platform: UNKNOWN
Classifier: Development Status :: 5 - Production/Stable
Classifier: Intended Audience :: Developers
Classifier: Intended Audience :: Education
Classifier: Intended Audience :: Science/Research
Classifier: Intended Audience :: Information Technology
Classifier: Intended Audience :: Financial and Insurance Industry
Classifier: Intended Audience :: Healthcare Industry
Classifier: Intended Audience :: Manufacturing
Classifier: License :: OSI Approved :: Apache Software License
Classifier: Operating System :: OS Independent
Classifier: Programming Language :: Python
Classifier: Programming Language :: Python :: 3
Classifier: Programming Language :: Python :: 3.6
Classifier: Programming Language :: Python :: 3.7
Classifier: Programming Language :: Python :: Implementation :: PyPy
Classifier: Topic :: Multimedia :: Sound/Audio :: Conversion
Classifier: Topic :: Multimedia :: Video :: Conversion
Classifier: Topic :: Scientific/Engineering :: Artificial Intelligence
Classifier: Topic :: Scientific/Engineering :: Image Recognition
Classifier: Topic :: Scientific/Engineering :: Information Analysis
Classifier: Topic :: Scientific/Engineering :: Visualization
Classifier: Topic :: Software Development :: Libraries :: Application Frameworks
Requires-Python: >=3
License-File: LICENSE
Requires-Dist: PyYAML
Requires-Dist: requests
Requires-Dist: document-utils
Requires-Dist: numpy
Provides-Extra: pillow
Requires-Dist: Pillow ; extra == 'pillow'
Provides-Extra: pyyaml
Requires-Dist: PyYAML ; extra == 'pyyaml'
Provides-Extra: all
Requires-Dist: imageio ; extra == 'all'
Requires-Dist: soundfile ; extra == 'all'
Requires-Dist: tensorflow (~=2.4.3) ; extra == 'all'
Requires-Dist: sphinx-rtd-theme (>=0.5.0) ; extra == 'all'
Requires-Dist: requests ; extra == 'all'
Requires-Dist: sentence-transformers ; extra == 'all'
Requires-Dist: moviepy ; extra == 'all'
Requires-Dist: document-utils ; extra == 'all'
Requires-Dist: scikit-image ; extra == 'all'
Requires-Dist: PyYAML ; extra == 'all'
Requires-Dist: torch (>=1.6.0) ; extra == 'all'
Requires-Dist: transformers ; extra == 'all'
Requires-Dist: fastai (==2.1.8) ; extra == 'all'
Requires-Dist: pytest ; extra == 'all'
Requires-Dist: torch (==1.7.1) ; extra == 'all'
Requires-Dist: appdirs ; extra == 'all'
Requires-Dist: mtcnn ; extra == 'all'
Requires-Dist: tf-models-official (==2.4.0) ; extra == 'all'
Requires-Dist: opencv-python ; extra == 'all'
Requires-Dist: tensorflow-text (~=2.4.3) ; extra == 'all'
Requires-Dist: Pillow ; extra == 'all'
Requires-Dist: librosa ; extra == 'all'
Requires-Dist: tensorflow-hub (~=0.12.0) ; extra == 'all'
Requires-Dist: fairseq ; extra == 'all'
Requires-Dist: numpy ; extra == 'all'
Requires-Dist: clip-by-openai ; extra == 'all'
Requires-Dist: bert-for-tf2 (==0.14.9) ; extra == 'all'
Provides-Extra: appdirs
Requires-Dist: appdirs ; extra == 'appdirs'
Provides-Extra: audio-encoder
Requires-Dist: librosa ; extra == 'audio-encoder'
Provides-Extra: bert-for-tf2_0.14.9
Requires-Dist: bert-for-tf2 (==0.14.9) ; extra == 'bert-for-tf2_0.14.9'
Provides-Extra: clip
Requires-Dist: Pillow ; extra == 'clip'
Requires-Dist: imageio ; extra == 'clip'
Requires-Dist: scikit-image ; extra == 'clip'
Requires-Dist: torch (==1.7.1) ; extra == 'clip'
Requires-Dist: clip-by-openai ; extra == 'clip'
Requires-Dist: opencv-python ; extra == 'clip'
Provides-Extra: clip-by-openai
Requires-Dist: clip-by-openai ; extra == 'clip-by-openai'
Provides-Extra: core
Requires-Dist: PyYAML ; extra == 'core'
Requires-Dist: requests ; extra == 'core'
Requires-Dist: document-utils ; extra == 'core'
Requires-Dist: numpy ; extra == 'core'
Provides-Extra: document-utils
Requires-Dist: document-utils ; extra == 'document-utils'
Provides-Extra: encoders-audio-pytorch
Requires-Dist: fairseq ; extra == 'encoders-audio-pytorch'
Requires-Dist: torch (>=1.6.0) ; extra == 'encoders-audio-pytorch'
Provides-Extra: encoders-audio-tfhub
Requires-Dist: tensorflow-hub (~=0.12.0) ; extra == 'encoders-audio-tfhub'
Requires-Dist: soundfile ; extra == 'encoders-audio-tfhub'
Requires-Dist: tensorflow (~=2.4.3) ; extra == 'encoders-audio-tfhub'
Requires-Dist: librosa ; extra == 'encoders-audio-tfhub'
Provides-Extra: encoders-code-transformers
Requires-Dist: transformers ; extra == 'encoders-code-transformers'
Requires-Dist: torch (>=1.6.0) ; extra == 'encoders-code-transformers'
Provides-Extra: encoders-image
Requires-Dist: imageio ; extra == 'encoders-image'
Requires-Dist: scikit-image ; extra == 'encoders-image'
Provides-Extra: encoders-image-cv2
Requires-Dist: opencv-python ; extra == 'encoders-image-cv2'
Provides-Extra: encoders-image-fastai
Requires-Dist: fastai (==2.1.8) ; extra == 'encoders-image-fastai'
Requires-Dist: torch (>=1.6.0) ; extra == 'encoders-image-fastai'
Provides-Extra: encoders-image-tf-face-detection
Requires-Dist: Pillow ; extra == 'encoders-image-tf-face-detection'
Requires-Dist: tensorflow (~=2.4.3) ; extra == 'encoders-image-tf-face-detection'
Requires-Dist: appdirs ; extra == 'encoders-image-tf-face-detection'
Requires-Dist: mtcnn ; extra == 'encoders-image-tf-face-detection'
Requires-Dist: opencv-python ; extra == 'encoders-image-tf-face-detection'
Provides-Extra: encoders-image-tfhub
Requires-Dist: imageio ; extra == 'encoders-image-tfhub'
Requires-Dist: scikit-image ; extra == 'encoders-image-tfhub'
Requires-Dist: tensorflow (~=2.4.3) ; extra == 'encoders-image-tfhub'
Requires-Dist: tensorflow-hub (~=0.12.0) ; extra == 'encoders-image-tfhub'
Provides-Extra: encoders-text-sentence-transformers
Requires-Dist: torch (>=1.6.0) ; extra == 'encoders-text-sentence-transformers'
Requires-Dist: sentence-transformers ; extra == 'encoders-text-sentence-transformers'
Provides-Extra: encoders-text-tf-transformers
Requires-Dist: transformers ; extra == 'encoders-text-tf-transformers'
Requires-Dist: tensorflow (~=2.4.3) ; extra == 'encoders-text-tf-transformers'
Provides-Extra: encoders-text-tfhub
Requires-Dist: tensorflow-text (~=2.4.3) ; extra == 'encoders-text-tfhub'
Requires-Dist: tensorflow (~=2.4.3) ; extra == 'encoders-text-tfhub'
Requires-Dist: tensorflow-hub (~=0.12.0) ; extra == 'encoders-text-tfhub'
Requires-Dist: tf-models-official (==2.4.0) ; extra == 'encoders-text-tfhub'
Requires-Dist: bert-for-tf2 (==0.14.9) ; extra == 'encoders-text-tfhub'
Provides-Extra: encoders-text-tfhub-windows
Requires-Dist: tf-models-official (==2.4.0) ; extra == 'encoders-text-tfhub-windows'
Requires-Dist: tensorflow-hub (~=0.12.0) ; extra == 'encoders-text-tfhub-windows'
Requires-Dist: tensorflow (~=2.4.3) ; extra == 'encoders-text-tfhub-windows'
Requires-Dist: bert-for-tf2 (==0.14.9) ; extra == 'encoders-text-tfhub-windows'
Provides-Extra: encoders-text-torch-transformers
Requires-Dist: transformers ; extra == 'encoders-text-torch-transformers'
Requires-Dist: torch (>=1.6.0) ; extra == 'encoders-text-torch-transformers'
Provides-Extra: encoders-video
Requires-Dist: moviepy ; extra == 'encoders-video'
Requires-Dist: opencv-python ; extra == 'encoders-video'
Provides-Extra: fairseq
Requires-Dist: fairseq ; extra == 'fairseq'
Provides-Extra: fastai_2.1.8
Requires-Dist: fastai (==2.1.8) ; extra == 'fastai_2.1.8'
Provides-Extra: imageio
Requires-Dist: imageio ; extra == 'imageio'
Provides-Extra: librosa
Requires-Dist: librosa ; extra == 'librosa'
Provides-Extra: moviepy
Requires-Dist: moviepy ; extra == 'moviepy'
Provides-Extra: mtcnn
Requires-Dist: mtcnn ; extra == 'mtcnn'
Provides-Extra: numpy
Requires-Dist: numpy ; extra == 'numpy'
Provides-Extra: opencv-python
Requires-Dist: opencv-python ; extra == 'opencv-python'
Provides-Extra: pytest
Requires-Dist: pytest ; extra == 'pytest'
Provides-Extra: requests
Requires-Dist: requests ; extra == 'requests'
Provides-Extra: scikit-image
Requires-Dist: scikit-image ; extra == 'scikit-image'
Provides-Extra: sentence-transformers
Requires-Dist: sentence-transformers ; extra == 'sentence-transformers'
Provides-Extra: soundfile
Requires-Dist: soundfile ; extra == 'soundfile'
Provides-Extra: sphinx-rtd-theme_0.5.0
Requires-Dist: sphinx-rtd-theme (>=0.5.0) ; extra == 'sphinx-rtd-theme_0.5.0'
Provides-Extra: tensorflow-hub_0.12.0
Requires-Dist: tensorflow-hub (~=0.12.0) ; extra == 'tensorflow-hub_0.12.0'
Provides-Extra: tensorflow-text_2.4.3
Requires-Dist: tensorflow-text (~=2.4.3) ; extra == 'tensorflow-text_2.4.3'
Provides-Extra: tensorflow_2.4.3
Requires-Dist: tensorflow (~=2.4.3) ; extra == 'tensorflow_2.4.3'
Provides-Extra: test
Requires-Dist: sphinx-rtd-theme (>=0.5.0) ; extra == 'test'
Requires-Dist: pytest ; extra == 'test'
Provides-Extra: tf-models-official_2.4.0
Requires-Dist: tf-models-official (==2.4.0) ; extra == 'tf-models-official_2.4.0'
Provides-Extra: torch_1.7.1
Requires-Dist: torch (==1.7.1) ; extra == 'torch_1.7.1'
Provides-Extra: torch_1.6.0
Requires-Dist: torch (>=1.6.0) ; extra == 'torch_1.6.0'
Provides-Extra: transformers
Requires-Dist: transformers ; extra == 'transformers'
